odoo/addons/beesdoo_print_label/README.rst
odoo/addons/beesdoo_print_label/__init__.py
odoo/addons/beesdoo_print_label/__manifest__.py
odoo/addons/beesdoo_print_label/data/product_print_category.xml
odoo/addons/beesdoo_print_label/i18n/beesdoo_print_label.pot
odoo/addons/beesdoo_print_label/i18n/fr.po
odoo/addons/beesdoo_print_label/readme/CONTRIBUTORS.rst
odoo/addons/beesdoo_print_label/readme/DESCRIPTION.rst
odoo/addons/beesdoo_print_label/static/css/pricetag_base.scss
odoo/addons/beesdoo_print_label/static/css/pricetag_normal_base.scss
odoo/addons/beesdoo_print_label/static/css/pricetag_normal_normal.scss
odoo/addons/beesdoo_print_label/static/description/index.html
odoo/addons/beesdoo_print_label/static/img/deposit.gif
odoo/addons/beesdoo_print_label/views/report_pricetag_normal.xml
odoo12_addon_beesdoo_print_label-12.0.1.1.1.99.dev8.dist-info/METADATA
odoo12_addon_beesdoo_print_label-12.0.1.1.1.99.dev8.dist-info/WHEEL
odoo12_addon_beesdoo_print_label-12.0.1.1.1.99.dev8.dist-info/top_level.txt
odoo12_addon_beesdoo_print_label-12.0.1.1.1.99.dev8.dist-info/RECORD
