Metadata-Version: 2.1
Name: odoo12-addon-beesdoo-print-label
Version: 12.0.1.1.1.99.dev8
Summary: Product labels
Home-page: https://github.com/beescoop/Obeesdoo
Author: Coop IT Easy SCRLfs
License: AGPL-3
Platform: UNKNOWN
Classifier: Programming Language :: Python
Classifier: Framework :: Odoo
Classifier: Framework :: Odoo :: 12.0
Classifier: License :: OSI Approved :: GNU Affero General Public License v3
Requires-Python: >=3.5
Requires-Dist: odoo12-addon-beesdoo-product
Requires-Dist: odoo12-addon-product-print-category
Requires-Dist: odoo (<12.1dev,>=12.0a)
